{
  "results": [
    {
      "kind": "PASS",
      "id": "J2.setup",
      "detail": "org GroundCo + gc-u1 builder ready (userId=92dd0b3d-8461-4746-a6cf-a052ce173fbd)"
    },
    {
      "kind": "PASS",
      "id": "J2.doc",
      "detail": "knowledge doc ingested id=4d91cbd5-f081-49b6-95a8-b0dbc5b8f233"
    },
    {
      "kind": "PASS",
      "id": "J2.terminal",
      "detail": "run 15eac10c-cc67-4f7e-be9c-b4e99d73f11e reached complete terminal"
    },
    {
      "kind": "PASS",
      "id": "J2.reply",
      "detail": "reply captured (385 chars): \"Com base na base de conhecimento da organização: - **Prazo de reembolso da GroundCo:** **11 dias úteis** - **Código inte\""
    },
    {
      "kind": "INFO",
      "id": "J2.completeTail",
      "detail": "complete.result is a 25-char TAIL; full answer (385 chars) only via text_chunk stream"
    },
    {
      "kind": "PASS",
      "id": "J2.grounded",
      "detail": "reply contains BOTH seeded facts (11 dias úteis + RX-417)"
    },
    {
      "kind": "INFO",
      "id": "J2.contextEvents",
      "detail": "context_event frames=0; knowledge tool_event frames=4"
    },
    {
      "kind": "PASS",
      "id": "J2.usageUpdated",
      "detail": "notifications channel pushed usage_updated"
    },
    {
      "kind": "INFO",
      "id": "J2.chatAnswer",
      "detail": "chat_answer notification not emitted (expected for plain chat — answer rides run-SSE)"
    },
    {
      "kind": "PASS",
      "id": "J2.persisted",
      "detail": "session has persisted turn (user+assistant, 2 msgs)"
    },
    {
      "kind": "PASS",
      "id": "J2.billing",
      "detail": "billing history has 3 row(s) after chat; chat-ish row=true"
    }
  ],
  "detail": {
    "setup": {
      "orgId": "57ff1c38-3544-4a32-8723-38a1285e8486",
      "userId": "92dd0b3d-8461-4746-a6cf-a052ce173fbd",
      "hasToken": true
    },
    "document": {
      "status": 201,
      "body": {
        "id": "4d91cbd5-f081-49b6-95a8-b0dbc5b8f233"
      }
    },
    "session": {
      "status": 201,
      "id": "29d86261-0eb9-4e6c-a106-5e03b72db5fa"
    },
    "turn": {
      "create": {
        "status": 202,
        "body": {
          "runId": "15eac10c-cc67-4f7e-be9c-b4e99d73f11e"
        }
      },
      "runId": "15eac10c-cc67-4f7e-be9c-b4e99d73f11e",
      "sseClosedReason": "until",
      "frames": [
        {
          "event": "ready",
          "id": "33",
          "data": {
            "stream": "chat",
            "id": "15eac10c-cc67-4f7e-be9c-b4e99d73f11e"
          }
        },
        {
          "event": "tool_event",
          "id": "34",
          "data": {
            "type": "tool_event",
            "phase": "started",
            "tool": "ToolSearch",
            "args": {
              "query": "select:mcp__ekoa__knowledge_search",
              "max_results": 1
            }
          }
        },
        {
          "event": "tool_event",
          "id": "35",
          "data": {
            "type": "tool_event",
            "phase": "finished",
            "tool": "tool",
            "result": "[{\"type\":\"tool_reference\",\"tool_name\":\"mcp__ekoa__knowledge_search\"}]",
            "isError": false
          }
        },
        {
          "event": "tool_event",
          "id": "36",
          "data": {
            "type": "tool_event",
            "phase": "started",
            "tool": "mcp__ekoa__knowledge_search",
            "args": {
              "query": "GroundCo prazo reembolso código interno processo",
              "limit": 5
            }
          }
        },
        {
          "event": "tool_event",
          "id": "37",
          "data": {
            "type": "tool_event",
            "phase": "finished",
            "tool": "tool",
            "result": "[{\"type\":\"text\",\"text\":\"- [politica-interna/8a5ead9e-32a6-410a-a503-3a48c9c9afd7] Política de reembolsos GroundCo\\n   … reembolso da GroundCo é de 11 dias úteis e o código interno … \\n- [politica-inte",
            "isError": false
          }
        },
        {
          "event": "text_chunk",
          "id": "38",
          "data": {
            "type": "text_chunk",
            "text": "Com base na base de conhecimento da organização:\n\n- **Prazo de reembolso da GroundCo:** **11 dias úteis**\n- **Código interno do processo:** A informação está parcialmente truncada no excerto. Vou ler o documento completo p"
          }
        },
        {
          "event": "tool_event",
          "id": "39",
          "data": {
            "type": "tool_event",
            "phase": "started",
            "tool": "ToolSearch",
            "args": {
              "query": "select:mcp__ekoa__knowledge_read",
              "max_results": 1
            }
          }
        },
        {
          "event": "tool_event",
          "id": "40",
          "data": {
            "type": "tool_event",
            "phase": "finished",
            "tool": "tool",
            "result": "[{\"type\":\"tool_reference\",\"tool_name\":\"mcp__ekoa__knowledge_read\"}]",
            "isError": false
          }
        },
        {
          "event": "tool_event",
          "id": "41",
          "data": {
            "type": "tool_event",
            "phase": "started",
            "tool": "mcp__ekoa__knowledge_read",
            "args": {
              "collection": "politica-interna",
              "docId": "8a5ead9e-32a6-410a-a503-3a48c9c9afd7"
            }
          }
        },
        {
          "event": "tool_event",
          "id": "42",
          "data": {
            "type": "tool_event",
            "phase": "finished",
            "tool": "tool",
            "result": "[{\"type\":\"text\",\"text\":\"# Política de reembolsos GroundCo\\n\\nO prazo de reembolso da GroundCo é de 11 dias úteis e o código interno do processo é RX-417.\"}]",
            "isError": false
          }
        },
        {
          "event": "text_chunk",
          "id": "43",
          "data": {
            "type": "text_chunk",
            "text": "ara obter o código exato.Aqui estão as informações completas:\n\n- **Prazo de reembolso da GroundCo:** **11 dias úteis**\n- **Código interno "
          }
        },
        {
          "event": "text_chunk",
          "id": "45",
          "data": {
            "type": "text_chunk",
            "text": "do processo:** **RX-417**"
          }
        },
        {
          "event": "complete",
          "id": "46",
          "data": {
            "type": "complete",
            "result": "do processo:** **RX-417**",
            "durationMs": 17942
          }
        }
      ],
      "terminalFrame": {
        "event": "complete",
        "id": "46",
        "data": {
          "type": "complete",
          "result": "do processo:** **RX-417**",
          "durationMs": 17942
        }
      },
      "terminalType": "complete",
      "reply": "Com base na base de conhecimento da organização:\n\n- **Prazo de reembolso da GroundCo:** **11 dias úteis**\n- **Código interno do processo:** A informação está parcialmente truncada no excerto. Vou ler o documento completo para obter o código exato.Aqui estão as informações completas:\n\n- **Prazo de reembolso da GroundCo:** **11 dias úteis**\n- **Código interno do processo:** **RX-417**",
      "replyFromComplete": "do processo:** **RX-417**",
      "replyFromChunks": "Com base na base de conhecimento da organização:\n\n- **Prazo de reembolso da GroundCo:** **11 dias úteis**\n- **Código interno do processo:** A informação está parcialmente truncada no excerto. Vou ler o documento completo para obter o código exato.Aqui estão as informações completas:\n\n- **Prazo de reembolso da GroundCo:** **11 dias úteis**\n- **Código interno do processo:** **RX-417**",
      "contextEvents": [],
      "toolEvents": [
        {
          "type": "tool_event",
          "phase": "started",
          "tool": "ToolSearch",
          "args": {
            "query": "select:mcp__ekoa__knowledge_search",
            "max_results": 1
          }
        },
        {
          "type": "tool_event",
          "phase": "finished",
          "tool": "tool",
          "result": "[{\"type\":\"tool_reference\",\"tool_name\":\"mcp__ekoa__knowledge_search\"}]",
          "isError": false
        },
        {
          "type": "tool_event",
          "phase": "started",
          "tool": "mcp__ekoa__knowledge_search",
          "args": {
            "query": "GroundCo prazo reembolso código interno processo",
            "limit": 5
          }
        },
        {
          "type": "tool_event",
          "phase": "finished",
          "tool": "tool",
          "result": "[{\"type\":\"text\",\"text\":\"- [politica-interna/8a5ead9e-32a6-410a-a503-3a48c9c9afd7] Política de reembolsos GroundCo\\n   … reembolso da GroundCo é de 11 dias úteis e o código interno … \\n- [politica-inte",
          "isError": false
        },
        {
          "type": "tool_event",
          "phase": "started",
          "tool": "ToolSearch",
          "args": {
            "query": "select:mcp__ekoa__knowledge_read",
            "max_results": 1
          }
        },
        {
          "type": "tool_event",
          "phase": "finished",
          "tool": "tool",
          "result": "[{\"type\":\"tool_reference\",\"tool_name\":\"mcp__ekoa__knowledge_read\"}]",
          "isError": false
        },
        {
          "type": "tool_event",
          "phase": "started",
          "tool": "mcp__ekoa__knowledge_read",
          "args": {
            "collection": "politica-interna",
            "docId": "8a5ead9e-32a6-410a-a503-3a48c9c9afd7"
          }
        },
        {
          "type": "tool_event",
          "phase": "finished",
          "tool": "tool",
          "result": "[{\"type\":\"text\",\"text\":\"# Política de reembolsos GroundCo\\n\\nO prazo de reembolso da GroundCo é de 11 dias úteis e o código interno do processo é RX-417.\"}]",
          "isError": false
        }
      ],
      "notif": {
        "status": 200,
        "errorBody": null,
        "frames": [
          {
            "event": "ready",
            "id": "32",
            "data": {
              "stream": "notifications",
              "id": "68271b09-6e60-49f0-a228-993413a9733a"
            }
          },
          {
            "event": "usage_updated",
            "id": "44",
            "data": {}
          }
        ],
        "sawUsageUpdated": true,
        "sawChatAnswer": false
      }
    },
    "grounding": {
      "contextEvents": [],
      "knowledgeToolEvents": [
        {
          "type": "tool_event",
          "phase": "started",
          "tool": "ToolSearch",
          "args": {
            "query": "select:mcp__ekoa__knowledge_search",
            "max_results": 1
          }
        },
        {
          "type": "tool_event",
          "phase": "started",
          "tool": "mcp__ekoa__knowledge_search",
          "args": {
            "query": "GroundCo prazo reembolso código interno processo",
            "limit": 5
          }
        },
        {
          "type": "tool_event",
          "phase": "started",
          "tool": "ToolSearch",
          "args": {
            "query": "select:mcp__ekoa__knowledge_read",
            "max_results": 1
          }
        },
        {
          "type": "tool_event",
          "phase": "started",
          "tool": "mcp__ekoa__knowledge_read",
          "args": {
            "collection": "politica-interna",
            "docId": "8a5ead9e-32a6-410a-a503-3a48c9c9afd7"
          }
        }
      ]
    },
    "messages": {
      "status": 200,
      "count": 2,
      "roles": [
        "user",
        "assistant"
      ]
    },
    "billing": {
      "status": 200,
      "count": 3,
      "rows": [
        {
          "id": "b0d00f98-187c-43c7-854f-b6b1089e7985",
          "type": "chat",
          "amountUsd": 0,
          "createdAt": "2026-07-08T18:30:57.416Z",
          "description": "1630 tokens",
          "tokens": 1630
        },
        {
          "id": "c53c03d2-b0a9-4763-8147-cfedf6e72ab3",
          "type": "memory-extract",
          "amountUsd": 0,
          "createdAt": "2026-07-08T18:28:54.917Z",
          "description": "101 tokens",
          "tokens": 101
        },
        {
          "id": "b7ccc645-ff94-413d-ae87-da79f112d8c2",
          "type": "chat",
          "amountUsd": 0,
          "createdAt": "2026-07-08T18:28:43.969Z",
          "description": "1749 tokens",
          "tokens": 1749
        }
      ]
    }
  }
}
